{
    "Name": "calendarTest1",
    "Content": {
        "schemaVersion": "2.2",
        "description": "Command Document Example Create JSON Template",
        "parameters": {
            "Message": {
                "type": "String",
                "description": "Example",
                "default": "Hello World"
            }
        },
        "mainSteps": [
            {
                "action": "aws:runPowerShellScript",
                "name": "example",
                "inputs": {
                    "runCommand": [
                        "Write-Output {{Message}}"
                    ]
                }
            }
        ]
    },
    "DocumentType": "ChangeCalendar",
    "DocumentFormat": "TEXT",
    "Tags": [
        {
            "Key": "CanaryTagKey",
            "Value": "CanaryTagValueA"
        }
    ]
}
